.gitignore
LICENSE
README.md
installer.bat
requirments.txt
setup.py
_install_/_RUN_INSTALLER_BAT_FROM_ROOT_FOLDER.txt
_install_/create_new_tool.ps1
_install_/get_latest_version.ps1
_install_/install_maya_module.bat
_install_/uninstall_maya_module.bat
_install_/scripts/userSetup.py
docs/example_image.PNG
docs/header_image.png
json_editor/__init__.py
json_editor/json_editor_dcc_setup.py
json_editor/json_editor_ui.py
json_editor/json_editor_utils.py
json_editor/icons/__init__.py
json_editor/icons/json_editor_icon.png
json_editor/ui/__init__.py
json_editor/ui/json_editor_ui.ui
json_editor_pyside6.egg-info/PKG-INFO
json_editor_pyside6.egg-info/SOURCES.txt
json_editor_pyside6.egg-info/dependency_links.txt
json_editor_pyside6.egg-info/requires.txt
json_editor_pyside6.egg-info/top_level.txt