Metadata-Version: 2.1
Name: json-editor-pyside6
Version: 1.0.3
Summary: Visual JSON Editor written in Qt
Home-page: https://github.com/eyalk11/json-editor-pyside6
Author: Richard Brenick, Eyal Karni
Author-email: RichardBrenick@gmail.com, eyalk5@gmail.com
License: UNKNOWN
Platform: UNKNOWN
Classifier: Programming Language :: Python :: 3
Classifier: License :: OSI Approved :: MIT License
Classifier: Operating System :: OS Independent
License-File: LICENSE
